Metadata-Version: 2.1
Name: haproxysubdomains
Version: 0.1.0
Summary: Manages redirect rules in haproxy configuration based on subdomain acl.
Home-page: https://github.com/ibizaman/haproxysubdomains
Author: Pierre Penninckx
Author-email: ibizapeanut@gmail.com
License: GPLv3
Download-URL: https://github.com/ibizaman/haproxysubdomains/archive/0.1.0.tar.gz
Keywords: haproxy
Platform: UNKNOWN
Provides-Extra: dev
Provides-Extra: test
